kafkahood_python/__init__.py
kafkahood_python/cli.py
kafkahood_python/kafkahood_python.py
kafkahood_python-0.1.0.dist-info/METADATA
kafkahood_python-0.1.0.dist-info/WHEEL
kafkahood_python-0.1.0.dist-info/entry_points.txt
kafkahood_python-0.1.0.dist-info/top_level.txt
kafkahood_python-0.1.0.dist-info/RECORD
