Metadata-Version: 2.1
Name: kafkahood-python
Version: 0.1.0
Summary: Python CLI for the Kafkahood Meetup group in Fayetteville, NC
Home-page: https://github.com/allanbreyes/kafkahood_python
Author: Allan Reyes
Author-email: pypi@reyes.sh
License: UNKNOWN
Keywords: kafkahood-python
Platform: UNKNOWN
Classifier: Development Status :: 2 - Pre-Alpha
Classifier: Intended Audience :: Developers
Classifier: Natural Language :: English
Classifier: Programming Language :: Python :: 3
Classifier: Programming Language :: Python :: 3.5
Classifier: Programming Language :: Python :: 3.6
Classifier: Programming Language :: Python :: 3.7
Classifier: Programming Language :: Python :: 3.8
Requires-Python: >=3.5
Requires-Dist: Click (>=7.0)
